genat_iso_parser/Iso.py
genat_iso_parser/__init__.py
genat_iso_parser/exceptions.py
iso_res/ISO_0.json
iso_res/ISO_1.json
iso_res/__init__.py
genat_iso_parser-1.2.dist-info/LICENSE
genat_iso_parser-1.2.dist-info/METADATA
genat_iso_parser-1.2.dist-info/WHEEL
genat_iso_parser-1.2.dist-info/top_level.txt
genat_iso_parser-1.2.dist-info/RECORD
