Metadata-Version: 2.2
Name: genat_iso_parser
Version: 1.2
Summary: An iso message bulk parser
Author-email: Nathnael Fikru <natfik2020@gmail.com>
Classifier: Programming Language :: Python :: 3
Classifier: License :: OSI Approved :: MIT License
Classifier: Operating System :: OS Independent
License-File: LICENSE
